ABRSQOL/__init__.py
ABRSQOL/invert_quality_of_life.py
ABRSQOL/testdata.py
ABRSQOL-1.0.2.dist-info/LICENSE
ABRSQOL-1.0.2.dist-info/METADATA
ABRSQOL-1.0.2.dist-info/WHEEL
ABRSQOL-1.0.2.dist-info/entry_points.txt
ABRSQOL-1.0.2.dist-info/top_level.txt
ABRSQOL-1.0.2.dist-info/RECORD
