Metadata-Version: 2.1
Name: ABRSQOL
Version: 1.0.2
Summary: Numerical solution algorithm to invert a quality of life measure.
Home-page: https://github.com/Ahlfeldt/ABRSQOL-toolkit-python
Author: Gabriel M Ahlfeldt
Author-email: g.ahlfeldt@hu-berlin.de
License: MIT
Classifier: Programming Language :: Python
Classifier: Programming Language :: Python :: 3
License-File: LICENSE
Requires-Dist: numpy
Requires-Dist: pandas
Provides-Extra: ci
Requires-Dist: pytest>=4; extra == "ci"
Requires-Dist: pytest-cov>=2; extra == "ci"
Requires-Dist: python-coveralls; extra == "ci"
Provides-Extra: dev
Requires-Dist: pytest>=4; extra == "dev"
Requires-Dist: pytest-cov>=2; extra == "dev"
Requires-Dist: twine>=4.0.2; extra == "dev"
Provides-Extra: test
Requires-Dist: pytest>=4; extra == "test"
Requires-Dist: pytest-cov>=2; extra == "test"
